{
  "generator-jhipster": {
    "applicationType": "monolith",
    "authenticationType": "jwt",
    "baseName": "phatnguoi",
    "buildTool": "maven",
    "cacheProvider": "no",
    "clientFramework": "angular",
    "clientTestFrameworks": [],
    "clientTheme": "none",
    "creationTimestamp": 1731850975779,
    "databaseType": "sql",
    "devDatabaseType": "oracle",
    "devServerPort": 4200,
    "enableHibernateCache": false,
    "enableSwaggerCodegen": true,
    "enableTranslation": true,
    "entities": ["CCCD", "TypeViolation", "VehicleRegistrations", "Violations"],
    "feignClient": null,
    "jhipsterVersion": "8.7.1",
    "jwtSecretKey": "M2Y1MzhiNGI3Mjk4Mzc4NzcxMDZhNGFmNzE5ZTczYWViOWZhYzQ5YmI3MmFkYTY4YzQ2NzgzOTA1ODBkMjY4YWZmYjE1NzFkNTRmNjU4ZTIxZDY1NGRiNGRmNGNmMGQzZmJhODBjMjA1NTNiMTQ2MWVlYTJiNTRmYTRkNzU3NmE=",
    "languages": ["en", "vi"],
    "lastLiquibaseTimestamp": 1731856831000,
    "messageBroker": false,
    "microfrontend": null,
    "microfrontends": [],
    "nativeLanguage": "en",
    "packageName": "com.mycompany.myapp",
    "prodDatabaseType": "oracle",
    "reactive": false,
    "searchEngine": false,
    "serverPort": null,
    "serverSideOptions": ["enableSwaggerCodegen:true"],
    "serviceDiscoveryType": false,
    "syncUserWithIdp": null,
    "testFrameworks": [],
    "websocket": false,
    "withAdminUi": true
  }
}
